exaspim_pipeline_utils/__init__.py
exaspim_pipeline_utils/__main__.py
exaspim_pipeline_utils/imagej_macros.py
exaspim_pipeline_utils/imagej_wrapper.py
exaspim_pipeline_utils-0.1.3.dist-info/LICENSE
exaspim_pipeline_utils-0.1.3.dist-info/METADATA
exaspim_pipeline_utils-0.1.3.dist-info/WHEEL
exaspim_pipeline_utils-0.1.3.dist-info/entry_points.txt
exaspim_pipeline_utils-0.1.3.dist-info/top_level.txt
exaspim_pipeline_utils-0.1.3.dist-info/RECORD
